manini/__init__.py
manini/_widget.py
manini/napari.yaml
manini/script2.py
manini/utils.py
manini/_tests/__init__.py
manini/_tests/test_widget.py
manini-0.0.11.dist-info/METADATA
manini-0.0.11.dist-info/WHEEL
manini-0.0.11.dist-info/entry_points.txt
manini-0.0.11.dist-info/top_level.txt
manini-0.0.11.dist-info/RECORD
