Metadata-Version: 2.1
Name: manini
Version: 0.0.11
Summary: An user-friendly plugin that enables to annotate images from a pre-trained model (segmentation, classification, detection) given by an user.
Home-page: https://github.com/hereariim/manini
Author: Herearii Metuarea
Author-email: herearii.metuarea@gmail.com
License: BSD-3-Clause
Project-URL: Bug Tracker, https://github.com/hereariim/manini/issues
Project-URL: Documentation, https://github.com/hereariim/manini#README.md
Project-URL: Source Code, https://github.com/hereariim/manini
Project-URL: User Support, https://github.com/hereariim/manini/issues
Classifier: Development Status :: 2 - Pre-Alpha
Classifier: Framework :: napari
Classifier: Intended Audience :: Developers
Classifier: License :: OSI Approved :: BSD License
Classifier: Operating System :: OS Independent
Classifier: Programming Language :: Python
Classifier: Programming Language :: Python :: 3
Classifier: Programming Language :: Python :: 3 :: Only
Classifier: Programming Language :: Python :: 3.8
Classifier: Programming Language :: Python :: 3.9
Classifier: Programming Language :: Python :: 3.10
Classifier: Topic :: Scientific/Engineering :: Image Processing
Requires-Python: >=3.8
Requires-Dist: numpy
Requires-Dist: magicgui
Requires-Dist: qtpy
Requires-Dist: napari
Requires-Dist: scikit-image
Requires-Dist: pandas
Requires-Dist: opencv-python-headless
Requires-Dist: tensorflow
Requires-Dist: PyQt5
Provides-Extra: testing
Requires-Dist: tox; extra == "testing"
Requires-Dist: pytest; extra == "testing"
Requires-Dist: pytest-cov; extra == "testing"
Requires-Dist: pytest-qt; extra == "testing"
Requires-Dist: napari; extra == "testing"
Requires-Dist: pyqt5; extra == "testing"
Requires-Dist: pytest-xvfb; extra == "testing"
Requires-Dist: numpy; extra == "testing"
Requires-Dist: magicgui; extra == "testing"
Requires-Dist: qtpy; extra == "testing"
Requires-Dist: scikit-image; extra == "testing"
Requires-Dist: pandas; extra == "testing"
Requires-Dist: opencv-python-headless; extra == "testing"
Requires-Dist: tensorflow; extra == "testing"
